pyos/__init__.py
pyos/cli.py
pyos/config.py
pyos/exceptions.py
pyos/fmt.py
pyos/glob.py
pyos/lib.py
pyos/pathlib.py
pyos/provides.py
pyos/pyos.py
pyos/results.py
pyos/utils.py
pyos/version.py
pyos/db/__init__.py
pyos/db/constants.py
pyos/db/database.py
pyos/db/fs.py
pyos/db/lib.py
pyos/db/migrations.py
pyos/db/queries.py
pyos/db/schema.py
pyos/db/utils.py
pyos/fs/__init__.py
pyos/fs/nodes.py
pyos/fs/utils.py
pyos/os/__init__.py
pyos/os/nodb.py
pyos/os/path.py
pyos/os/types.py
pyos/os/withdb.py
pyos/psh/__init__.py
pyos/psh/argparse_types.py
pyos/psh/completion.py
pyos/psh/constants.py
pyos/psh/flags.py
pyos/psh/shell.py
pyos/psh/utils.py
pyos/psh/cmds/__init__.py
pyos/psh/cmds/cat.py
pyos/psh/cmds/cd.py
pyos/psh/cmds/connect.py
pyos/psh/cmds/find.py
pyos/psh/cmds/history.py
pyos/psh/cmds/load.py
pyos/psh/cmds/locate.py
pyos/psh/cmds/log.py
pyos/psh/cmds/ls.py
pyos/psh/cmds/meta.py
pyos/psh/cmds/mkdir.py
pyos/psh/cmds/mv.py
pyos/psh/cmds/oid.py
pyos/psh/cmds/pwd.py
pyos/psh/cmds/rm.py
pyos/psh/cmds/rsync.py
pyos/psh/cmds/save.py
pyos/psh/cmds/tree.py
pyos/psh_lib/__init__.py
pyos/psh_lib/opts.py
pyos/psh_lib/representers.py
pyos/psh_lib/results.py
pyos/psh_lib/utils.py
pyos-0.8.0.dist-info/LICENSE
pyos-0.8.0.dist-info/METADATA
pyos-0.8.0.dist-info/WHEEL
pyos-0.8.0.dist-info/entry_points.txt
pyos-0.8.0.dist-info/top_level.txt
pyos-0.8.0.dist-info/RECORD
