Metadata-Version: 2.1
Name: pyos
Version: 0.8.0
Summary: Browse python objects as if they were files on disk
Home-page: https://github.com/muhrin/pyos.git
Author: Martin Uhrin
Author-email: martin.uhrin.10@ucl.ac.uk
License: GPLv3
Project-URL: Documentation, https://pyos.readthedocs.org/
Project-URL: Source, https://github.com/muhrin/pyos/
Keywords: database schemaless nosql object-store
Platform: UNKNOWN
Classifier: License :: OSI Approved :: GNU General Public License v3 (GPLv3)
Classifier: Programming Language :: Python :: 3.7
Classifier: Programming Language :: Python :: 3.8
Classifier: Programming Language :: Python :: 3.9
Requires-Python: >=3.7
License-File: LICENSE
Requires-Dist: anytree
Requires-Dist: cmd2 (~=1.3.2)
Requires-Dist: columnize
Requires-Dist: mincepy (<0.17,>=0.16.1)
Requires-Dist: click
Requires-Dist: ipython
Requires-Dist: pandas
Requires-Dist: pymongo
Requires-Dist: pyprnt
Requires-Dist: pytray (>=0.3.0)
Requires-Dist: stevedore
Requires-Dist: tqdm
Requires-Dist: yarl
Provides-Extra: dev
Requires-Dist: cmd2-ext-test ; extra == 'dev'
Requires-Dist: ipython ; extra == 'dev'
Requires-Dist: jupyter-sphinx ; extra == 'dev'
Requires-Dist: nbsphinx ; extra == 'dev'
Requires-Dist: pip ; extra == 'dev'
Requires-Dist: pytest (>4) ; extra == 'dev'
Requires-Dist: pytest-cov ; extra == 'dev'
Requires-Dist: pre-commit ; extra == 'dev'
Requires-Dist: sphinx ; extra == 'dev'
Requires-Dist: sphinx-autobuild ; extra == 'dev'
Requires-Dist: yapf ; extra == 'dev'
Requires-Dist: pylint ; extra == 'dev'
Requires-Dist: twine ; extra == 'dev'
Provides-Extra: gui
Requires-Dist: mincepy[gui] ; extra == 'gui'
